sQQideR/DatabaseContext.cp312-win_amd64.pyd
sQQideR/QueryHistory.cp312-win_amd64.pyd
sQQideR/SQLBuilder.cp312-win_amd64.pyd
sQQideR/__init__.py
sqqider-0.1.0.dist-info/METADATA
sqqider-0.1.0.dist-info/WHEEL
sqqider-0.1.0.dist-info/top_level.txt
sqqider-0.1.0.dist-info/RECORD
